MANIFEST.in
VERSION
distribute_setup.py
setup.py
src/exchequer/__init__.py
src/exchequer.egg-info/PKG-INFO
src/exchequer.egg-info/SOURCES.txt
src/exchequer.egg-info/dependency_links.txt
src/exchequer.egg-info/top_level.txt