Metadata-Version: 1.0
Name: exchequer
Version: 0.0.1
Summary: Easy table formatting in Python and on the command-line.
Home-page: http://github.com/zacharyvoase/exchequer
Author: Zachary Voase
Author-email: z@zacharyvoase.com
License: UNKNOWN
Platform: UNKNOWN
